CHANGES.txt
LICENSE.txt
MANIFEST.in
README.txt
setup.py
vmfusion/__init__.py
vmfusion.egg-info/PKG-INFO
vmfusion.egg-info/SOURCES.txt
vmfusion.egg-info/dependency_links.txt
vmfusion.egg-info/requires.txt
vmfusion.egg-info/top_level.txt