Metadata-Version: 1.0
Name: vmfusion
Version: 0.1.1
Summary: A python API for the VMware Fusion CLI tools.
Home-page: https://github.com/msteinhoff/vmfusion-python
Author: Mario Steinhoff
Author-email: steinhoff.mario@gmail.com
License: LICENSE.txt
Platform: UNKNOWN
